super_cereal/__init__.py
super_cereal/cerealizer/__init__.py
super_cereal/cerealizer/avro.py
super_cereal/cerealizer/builtins.py
super_cereal/cerealizer/encryption.py
super_cereal/cerealizer/json.py
super_cereal-0.2.3.dist-info/LICENSE
super_cereal-0.2.3.dist-info/WHEEL
super_cereal-0.2.3.dist-info/METADATA
super_cereal-0.2.3.dist-info/RECORD
